pyOfficeLearn/__init__.py
pyOfficeLearn/__main__.py
pyOfficeLearn/config.json
pyOfficeLearn/pic/icon/240px-Refresh_icon.png
pyOfficeLearn/pic/icon/Refresh_icon.png
pyOfficeLearn/pic/icon/cellResize.png
pyOfficeLearn/pic/icon/code.png
pyOfficeLearn/pic/icon/cut_icon.png
pyOfficeLearn/pic/icon/execute.png
pyOfficeLearn/pic/icon/exportCSV.png
pyOfficeLearn/pic/icon/exportPDF.png
pyOfficeLearn/pic/icon/file.jpeg
pyOfficeLearn/pic/icon/file.png
pyOfficeLearn/pic/icon/link_sync.png
pyOfficeLearn/pic/icon/menu.png
pyOfficeLearn/pic/icon/newFile.png
pyOfficeLearn/pic/icon/printer.png
pyOfficeLearn/pic/icon/py-office-icon_small.png
pyOfficeLearn/pic/icon/pyoffice.png
pyOfficeLearn/pic/icon/save.png
pyOfficeLearn/pic/icon/user.png
pyOfficeLearn/pic/icon/warning.png
py_office_learn-0.1.151.dist-info/LICENSE
py_office_learn-0.1.151.dist-info/METADATA
py_office_learn-0.1.151.dist-info/WHEEL
py_office_learn-0.1.151.dist-info/entry_points.txt
py_office_learn-0.1.151.dist-info/top_level.txt
py_office_learn-0.1.151.dist-info/RECORD
