Metadata-Version: 2.1
Name: py-office-learn
Version: 0.1.151
Summary: py-office-learn is a gui for machine learning 
Home-page: https://github.com/YC-Lammy/py-office-learn
Author: YC
Author-email: yclam508@protonmail.com
License: GPL
Platform: Linux
Platform: Mac OS X
Platform: Windows
Classifier: License :: OSI Approved :: GNU General Public License v3 (GPLv3)
Classifier: Programming Language :: Python :: 3
Classifier: Programming Language :: Python :: 3.7
Classifier: Programming Language :: Python :: 3.8
Classifier: Programming Language :: Python :: 3.9
Classifier: Programming Language :: Python :: 3 :: Only
Requires-Dist: joblib
Requires-Dist: matplotlib
